{
  "major_arcana": [
    {
      "number": 0,
      "name": "바보",
      "keywords": ["순수", "모험", "자발성"],
      "element": "공기",
      "upright": {
        "general": "순수함, 새로운 시작, 자유로운 영혼",
        "love": "순수한 사랑, 새로운 만남, 자유로운 연애",
        "career": "새로운 도전, 창의적 시도, 자유로운 직업 선택",
        "self_growth": "편견 없는 학습, 새로운 시각, 자기 발견"
      },
      "reversed": {
        "general": "무모함, 위험한 선택, 부주의",
        "love": "비현실적 기대, 불안정한 관계, 책임감 부족",
        "career": "준비 부족, 계획성 결여, 실수",
        "self_growth": "방황, 미성숙, 현실 도피"
      },
      "description": "무한한 가능성을 상징하는 카드로, 새로운 시작과 순수한 에너지를 나타냅니다."
    },
    {
      "number": 1,
      "name": "마법사",
      "keywords": ["창조력", "의지", "숙련"],
      "element": "공기",
      "upright": {
        "general": "창조성, 행동력, 잠재력 실현",
        "love": "매력적인 대화, 적극적인 구애, 관계 발전",
        "career": "새로운 기회, 전문성 발휘, 기술 습득",
        "self_growth": "재능 개발, 자기 확신, 목표 달성"
      },
      "reversed": {
        "general": "의지 부족, 속임수, 기회 상실",
        "love": "거짓된 관계, 조작, 신뢰 상실",
        "career": "능력 미숙, 기회 놓침, 부정직",
        "self_growth": "자신감 결여, 재능 낭비, 미완성"
      },
      "description": "창조적 에너지와 의지력을 상징하며, 자신의 능력을 최대한 발휘하는 것을 나타냅니다."
    },
    {
      "number": 2,
      "name": "여사제",
      "keywords": ["직관", "지혜", "비밀"],
      "element": "물",
      "upright": {
        "general": "직관, 신비, 지혜",
        "love": "내적 통찰, 정신적 교감, 깊은 이해",
        "career": "학습 능력, 연구, 전문 지식",
        "self_growth": "영적 성장, 내면 탐구, 지혜 획득"
      },
      "reversed": {
        "general": "비밀 폭로, 혼란, 직관 부족",
        "love": "오해, 감정 억제, 소통 부족",
        "career": "지식 부족, 판단 오류, 불확실성",
        "self_growth": "자기 의심, 영적 혼란, 지혜 상실"
      },
      "description": "내면의 지혜와 직관력을 상징하며, 깊은 통찰과 신비로운 지식을 나타냅니다."
    },
    {
      "number": 3,
      "name": "여황제",
      "keywords": ["풍요", "모성", "창조"],
      "element": "땅",
      "upright": {
        "general": "풍요, 창조성, 보살핌",
        "love": "안정된 관계, 결혼, 가정의 화합",
        "career": "성과 달성, 물질적 성공, 안정",
        "self_growth": "자기 돌봄, 창조적 표현, 성숙"
      },
      "reversed": {
        "general": "의존, 무기력, 창조성 부족",
        "love": "과잉보호, 질식된 관계, 독립성 상실",
        "career": "생산성 저하, 재정적 어려움, 불안정",
        "self_growth": "자기 방임, 창조력 상실, 의존성"
      },
      "description": "풍요와 창조적 에너지를 상징하며, 물질적・정신적 풍요를 나타냅니다."
    },
    {
      "number": 4,
      "name": "황제",
      "keywords": ["권위", "질서", "성취"],
      "element": "불",
      "upright": {
        "general": "안정, 권위, 책임감",
        "love": "안정된 관계, 보호, 책임감 있는 파트너",
        "career": "리더십, 성공, 조직력",
        "self_growth": "자기 통제, 목표 달성, 규율"
      },
      "reversed": {
        "general": "독재, 경직된 사고, 무책임",
        "love": "지배적 관계, 억압, 자유 제한",
        "career": "권위 남용, 실패, 무질서",
        "self_growth": "자제력 상실, 고집, 융통성 부족"
      },
      "description": "권위와 질서를 상징하며, 안정적인 성취와 리더십을 나타냅니다."
    },
    {
      "number": 5,
      "name": "교황",
      "keywords": ["전통", "가르침", "신념"],
      "element": "땅",
      "upright": {
        "general": "전통, 교육, 영적 지도",
        "love": "전통적 관계, 결혼, 정신적 유대",
        "career": "멘토링, 교육, 전문성",
        "self_growth": "가치관 확립, 정신적 성장, 지식 전수"
      },
      "reversed": {
        "general": "독단, 관습 파괴, 오해",
        "love": "형식적 관계, 가치관 충돌, 제약",
        "career": "과도한 규제, 편견, 고정관념",
        "self_growth": "신념의 혼란, 가치관 상실, 불신"
      },
      "description": "전통적 가치와 교육을 상징하며, 정신적 지도와 가르침을 나타냅니다."
    },
    {
      "number": 6,
      "name": "연인",
      "keywords": ["사랑", "선택", "조화"],
      "element": "공기",
      "upright": {
        "general": "사랑, 조화, 선택",
        "love": "진정한 사랑, 조화로운 관계, 결합",
        "career": "협력, 팀워크, 좋은 선택",
        "self_growth": "자아 통합, 가치관 정립, 조화"
      },
      "reversed": {
        "general": "갈등, 신뢰 부족, 잘못된 선택",
        "love": "불화, 이별, 삼각관계",
        "career": "협력 실패, 갈등, 잘못된 판단",
        "self_growth": "내적 갈등, 가치관 혼란, 부조화"
      },
      "description": "사랑과 선택을 상징하며, 인간관계의 조화와 중요한 결정을 나타냅니다."
    },
    {
      "number": 7,
      "name": "전차",
      "keywords": ["진보", "승리", "의지"],
      "element": "불",
      "upright": {
        "general": "결단력, 승리, 통제력",
        "love": "열정적 관계, 진전, 성공적인 구애",
        "career": "성공, 진보, 목표 달성",
        "self_growth": "자기 통제, 의지력, 성취"
      },
      "reversed": {
        "general": "좌절, 무기력, 방향 상실",
        "love": "관계 정체, 실패한 구애, 통제 상실",
        "career": "목표 상실, 패배, 방향성 혼란",
        "self_growth": "자제력 상실, 의지 약화, 혼란"
      },
      "description": "의지력과 승리를 상징하며, 목표를 향한 진보와 성취를 나타냅니다."
    },
    {
      "number": 8,
      "name": "힘",
      "keywords": ["용기", "인내", "내적 힘"],
      "element": "불",
      "upright": {
        "general": "용기, 인내심, 내적 힘",
        "love": "안정된 사랑, 신뢰, 용기 있는 표현",
        "career": "도전 극복, 리더십, 자신감",
        "self_growth": "자기 통제, 내면의 힘, 성장"
      },
      "reversed": {
        "general": "불안, 의지 약화, 공포",
        "love": "자신감 결여, 불안정한 관계, 두려움",
        "career": "자신감 상실, 권위 상실, 약점",
        "self_growth": "내적 혼란, 자제력 상실, 불안"
      },
      "description": "내면의 힘과 용기를 상징하며, 자기 통제와 인내를 나타냅니다."
    },
    {
      "number": 9,
      "name": "은둔자",
      "keywords": ["성찰", "고독", "지혜"],
      "element": "땅",
      "upright": {
        "general": "내성, 고독, 자기 탐구",
        "love": "자기 성찰, 독신, 관계 재고",
        "career": "독립적 작업, 연구, 전문성",
        "self_growth": "명상, 자아 발견, 깊은 통찰"
      },
      "reversed": {
        "general": "외로움, 고립, 방향 상실",
        "love": "과도한 고립, 소통 부재, 관계 회피",
        "career": "고립된 업무, 소통 부족, 협력 실패",
        "self_growth": "자기 부정, 고립, 비사회성"
      },
      "description": "고독과 내면의 지혜를 상징하며, 자기 성찰과 깊은 통찰을 나타냅니다."
    },
    {
      "number": 10,
      "name": "운명의 수레바퀴",
      "keywords": ["운명", "순환", "변화"],
      "element": "불",
      "upright": {
        "general": "운명, 변화, 기회",
        "love": "운명적 만남, 관계의 전환, 새로운 단계",
        "career": "전환점, 승진, 새로운 기회",
        "self_growth": "운명적 깨달음, 인생의 전환, 성장"
      },
      "reversed": {
        "general": "저항, 불운, 예기치 않은 사건",
        "love": "불운한 관계, 변화 거부, 정체",
        "career": "실패, 기회 상실, 부정적 변화",
        "self_growth": "성장 저항, 변화 거부, 고착"
      },
      "description": "운명의 순환과 변화를 상징하며, 인생의 전환점을 나타냅니다."
    },
    {
      "number": 11,
      "name": "정의",
      "keywords": ["균형", "진실", "정의"],
      "element": "공기",
      "upright": {
        "general": "공정함, 진실, 책임",
        "love": "공평한 관계, 정직, 균형",
        "career": "공정한 평가, 법적 성공, 균형",
        "self_growth": "도덕성, 윤리의식, 균형 잡힌 판단"
      },
      "reversed": {
        "general": "불공정, 편견, 진실 은폐",
        "love": "불공평한 관계, 거짓말, 불균형",
        "career": "부당한 대우, 불법, 편파성",
        "self_growth": "도덕성 상실, 부정직, 불균형"
      },
      "description": "정의와 균형을 상징하며, 공정한 판단과 책임을 나타냅니다."
    },
    {
      "major_arcana": [
        {
          "number": 12,
          "name": "매달린 사람",
          "keywords": ["희생", "관점", "중단"],
          "element": "물",
          "upright": {
            "general": "희생, 새로운 관점, 중단",
            "love": "자기 희생, 기다림, 새로운 시각",
            "career": "일시적 중단, 새로운 접근, 희생",
            "self_growth": "관점 전환, 깨달음, 수용"
          },
          "reversed": {
            "general": "집착, 우유부단, 의미 없는 희생",
            "love": "불필요한 희생, 고착된 관계, 집착",
            "career": "시간 낭비, 무의미한 노력, 고집",
            "self_growth": "관점 고착, 깨달음 거부, 수동성"
          },
          "description": "희생과 새로운 관점을 상징하며, 일시적인 중단과 깊은 통찰을 나타냅니다."
        },
        {
          "number": 13,
          "name": "죽음",
          "keywords": ["변화", "종말", "재생"],
          "element": "물",
          "upright": {
            "general": "변화, 끝맺음, 새로운 시작",
            "love": "관계의 전환, 새로운 단계, 변화",
            "career": "경력 전환, 새로운 시작, 변화",
            "self_growth": "근본적 변화, 자아의 재생, 혁신"
          },
          "reversed": {
            "general": "저항, 두려움, 정체",
            "love": "변화 거부, 관계 정체, 두려움",
            "career": "변화 거부, 직업 정체, 두려움",
            "self_growth": "변화 저항, 성장 정체, 공포"
          },
          "description": "끝맺음과 새로운 시작을 상징하며, 근본적인 변화와 재생을 나타냅니다."
        },
        {
          "number": 14,
          "name": "절제",
          "keywords": ["균형", "조화", "중용"],
          "element": "불",
          "upright": {
            "general": "조화, 인내, 균형",
            "love": "안정된 관계, 조화로운 사랑, 절제",
            "career": "안정적 성장, 균형잡힌 발전, 조화",
            "self_growth": "자기 조절, 내적 조화, 중용"
          },
          "reversed": {
            "general": "과잉, 충동, 균형 상실",
            "love": "불안정한 관계, 과도한 감정, 불균형",
            "career": "불균형한 발전, 과로, 스트레스",
            "self_growth": "자제력 상실, 과도함, 불균형"
          },
          "description": "균형과 조화를 상징하며, 절제된 행동과 중용의 미덕을 나타냅니다."
        },
        {
          "number": 15,
          "name": "악마",
          "keywords": ["속박", "유혹", "집착"],
          "element": "땅",
          "upright": {
            "general": "집착, 유혹, 억압",
            "love": "불건전한 관계, 집착, 의존",
            "career": "부정적 상황, 착취, 중독",
            "self_growth": "자기 기만, 부정적 습관, 중독"
          },
          "reversed": {
            "general": "해방, 회복, 자제력",
            "love": "관계 회복, 집착 극복, 자유",
            "career": "부정적 상황 극복, 자유, 해방",
            "self_growth": "자기 극복, 해방, 치유"
          },
          "description": "속박과 유혹을 상징하며, 내면의 그림자와 욕망을 나타냅니다."
        },
        {
          "number": 16,
          "name": "탑",
          "keywords": ["파괴", "혁신", "해방"],
          "element": "불",
          "upright": {
            "general": "충격, 붕괴, 해방",
            "love": "급격한 변화, 관계 붕괴, 충격",
            "career": "급격한 변화, 실패, 혁신",
            "self_growth": "기존 가치관 붕괴, 각성, 해방"
          },
          "reversed": {
            "general": "저항, 파괴 방지, 두려움",
            "love": "변화 회피, 관계 유지, 두려움",
            "career": "변화 거부, 안주, 두려움",
            "self_growth": "변화 저항, 고착, 두려움"
          },
          "description": "급격한 변화와 붕괴를 상징하며, 필요한 파괴와 새로운 시작을 나타냅니다."
        },
        {
          "number": 17,
          "name": "별",
          "keywords": ["희망", "영감", "치유"],
          "element": "공기",
          "upright": {
            "general": "희망, 영감, 치유",
            "love": "희망적인 관계, 낭만, 치유",
            "career": "새로운 영감, 희망, 성공",
            "self_growth": "자기 치유, 영감, 희망"
          },
          "reversed": {
            "general": "좌절, 절망, 방향 상실",
            "love": "실망, 희망 상실, 좌절",
            "career": "영감 상실, 좌절, 실패",
            "self_growth": "자기 회의, 절망, 무기력"
          },
          "description": "희망과 영감을 상징하며, 치유와 새로운 가능성을 나타냅니다."
        },
        {
          "number": 18,
          "name": "달",
          "keywords": ["환상", "불안", "직관"],
          "element": "물",
          "upright": {
            "general": "환상, 직관, 불확실성",
            "love": "감정적 혼란, 불안정한 관계, 직관",
            "career": "불확실성, 혼란, 직관적 판단",
            "self_growth": "무의식 탐구, 직관력, 불안"
          },
          "reversed": {
            "general": "혼란 해소, 진실 발견, 안정",
            "love": "관계 명확화, 불안 해소, 안정",
            "career": "불확실성 해소, 명확성, 안정",
            "self_growth": "내면의 평화, 안정, 명확성"
          },
          "description": "무의식과 환상을 상징하며, 직관적 통찰과 불안을 나타냅니다."
        },
        {
          "number": 19,
          "name": "태양",
          "keywords": ["성공", "기쁨", "활력"],
          "element": "불",
          "upright": {
            "general": "성공, 행복, 활력",
            "love": "행복한 관계, 성취, 열정",
            "career": "성공, 인정, 성취",
            "self_growth": "자아실현, 행복, 성취"
          },
          "reversed": {
            "general": "자만심, 좌절, 에너지 부족",
            "love": "일시적 어려움, 열정 감소, 좌절",
            "career": "성공의 그늘, 번아웃, 좌절",
            "self_growth": "자신감 상실, 우울, 무기력"
          },
          "description": "성공과 행복을 상징하며, 밝은 에너지와 성취를 나타냅니다."
        },
        {
          "number": 20,
          "name": "심판",
          "keywords": ["부활", "각성", "변화"],
          "element": "불",
          "upright": {
            "general": "각성, 판단, 재생",
            "love": "관계의 재평가, 화해, 부활",
            "career": "재평가, 새로운 기회, 부활",
            "self_growth": "자아 각성, 용서, 재생"
          },
          "reversed": {
            "general": "자기 의심, 두려움, 후회",
            "love": "과거 집착, 용서 거부, 후회",
            "career": "기회 상실, 자책, 후회",
            "self_growth": "자기 부정, 후회, 두려움"
          },
          "description": "부활과 각성을 상징하며, 최종적인 판단과 새로운 시작을 나타냅니다."
        },
        {
          "number": 21,
          "name": "세계",
          "keywords": ["완성", "통합", "성취"],
          "element": "땅",
          "upright": {
            "general": "완성, 성취, 통합",
            "love": "이상적인 관계, 완성된 사랑, 조화",
            "career": "목표 달성, 완벽한 성공, 완성",
            "self_growth": "자아 완성, 통합, 성취"
          },
          "reversed": {
            "general": "미완성, 지연, 목표 상실",
            "love": "불완전한 관계, 미완성, 불만족",
            "career": "목표 미달성, 지연, 불완전",
            "self_growth": "불완전한 성장, 미완성, 공허"
          },
          "description": "완성과 성취를 상징하며, 모든 것의 통합과 완벽한 조화를 나타냅니다."
        }
      ]
    }
  ]}